README.md
setup.py
mandelbrot_implementations/__init__.py
mandelbrot_implementations/constant.py
mandelbrot_implementations/mandelbrot.py
mandelbrot_implementations/mandelbrot_1.py
mandelbrot_implementations/mandelbrot_2.py
mandelbrot_implementations/mandelbrot_3.py
mandelbrot_implementations/mandelbrot_4.py
mandelbrot_implementations_inf3331_michagu.egg-info/PKG-INFO
mandelbrot_implementations_inf3331_michagu.egg-info/SOURCES.txt
mandelbrot_implementations_inf3331_michagu.egg-info/dependency_links.txt
mandelbrot_implementations_inf3331_michagu.egg-info/requires.txt
mandelbrot_implementations_inf3331_michagu.egg-info/top_level.txt