Metadata-Version: 1.0
Name: mandelbrot-implementations-inf3331-michagu
Version: 1.2
Summary: Various implementations computing and drawing the mandelbrot_implementations set
Home-page: https://github.com/UiO-INF3331/INF3331-michagu/tree/master/assignment4/mandelbrot_implementations
Author: theagilepadawan
Author-email: michagu@ifi.uio.no
License: UNKNOWN
Keywords: inf3331 mandelbrot_implementations fractal
Platform: UNKNOWN
